sktda_docs_config/__init__.py
sktda_docs_config/better/__init__.py
sktda_docs_config/better/githubbox.html
sktda_docs_config/better/globaltoc.html
sktda_docs_config/better/layout.html
sktda_docs_config/better/relbar.html
sktda_docs_config/better/searchbox.html
sktda_docs_config/better/theme.conf
sktda_docs_config/better/__pycache__/__init__.cpython-37.pyc
sktda_docs_config/better/static/better.css_t
sktda_docs_config/better/static/better_basic.css_t
sktda_docs_config/better/static/better_sktda.css_t
sktda_docs_config/better/static/gh_logo.png
sktda_docs_config-0.0.8.dist-info/LICENSE
sktda_docs_config-0.0.8.dist-info/METADATA
sktda_docs_config-0.0.8.dist-info/WHEEL
sktda_docs_config-0.0.8.dist-info/top_level.txt
sktda_docs_config-0.0.8.dist-info/RECORD
