Metadata-Version: 2.1
Name: sktda-docs-config
Version: 0.0.8
Summary: Custom configuration for the Scikit-TDA documentation
Home-page: https://github.com/scikit-tda/sktda-docs-config
Author: Nathaniel Saul
Author-email: nat@riverasaul.com
License: MIT
Platform: UNKNOWN
Requires-Python: >3.3
Requires-Dist: sphinx
Requires-Dist: ipython
Requires-Dist: nbsphinx
Requires-Dist: sphinxcontrib-fulltoc
